{
  "name": "Ken — on Pension Credit, renting, adult son at home",
  "note": "Maximum Housing Benefit applies, but the page shows no amount: a non-dependant deduction for his son (sized by the son's income) is real and not encoded, so any number would overstate. The verdict says so instead.",
  "as_of": "2026-07-12",
  "checked": "Non-dependant deduction existence against HB (SPC) Regs 2006 reg 55 (amounts not encoded by design), 2026-07-12.",
  "answers": {
    "dob": "1949-11-11",
    "has_partner": false,
    "weekly_state_pension": 16000,
    "weekly_other_pensions": 0,
    "weekly_earnings": 0,
    "weekly_other_income": 0,
    "capital": 100000,
    "gets_disability_benefit": false,
    "other_adults": true,
    "carer_paid_for_you": false,
    "you_get_ca": false,
    "scotland": false,
    "aa_excluded": false,
    "aa_day": false,
    "aa_night": false,
    "aa_six_months": false,
    "gets_pc": true,
    "pays_rent": true,
    "weekly_rent": 11000,
    "income_over_35k": false,
    "cares_35h": false,
    "cared_for_gets_qualifying": false,
    "own_earnings": 0,
    "own_state_pension": 16000,
    "weekly_council_tax": 3100
  },
  "expect": {
    "pension-credit-guarantee": {
      "verdict": "appears-eligible",
      "weekly": 7800
    },
    "housing-benefit-pension-age": {
      "verdict": "appears-eligible",
      "weekly": null
    },
    "council-tax-reduction": {
      "verdict": "appears-eligible",
      "weekly": null
    }
  }
}
